optum_testbed_cli-0.1.4.data/scripts/install.sh
optum_testbed_cli-0.1.4.data/scripts/otbctl_directory.sh
otbctl/__init__.py
otbctl/__main__.py
otbctl/log_management.py
otbctl/otbctl_main.py
otbctl/otbctl_mock.py
otbctl/otbctl_server.py
otbctl/yaml_validate.py
optum_testbed_cli-0.1.4.dist-info/METADATA
optum_testbed_cli-0.1.4.dist-info/WHEEL
optum_testbed_cli-0.1.4.dist-info/entry_points.txt
optum_testbed_cli-0.1.4.dist-info/top_level.txt
optum_testbed_cli-0.1.4.dist-info/RECORD
