Metadata-Version: 2.1
Name: optum-testbed-cli
Version: 0.1.4
Summary: UNKNOWN
Home-page: https://github.optum.com/OCS-Transformation-Optimization/optum-testbed-cli
Author: Venkata Krishna Lolla
Author-email: venkata.lolla@optum.com
Maintainer: Venkata Krishna Lolla
License: UNKNOWN
Platform: UNKNOWN
Requires-Dist: python-dotenv
Requires-Dist: requests
Requires-Dist: pyyaml
Requires-Dist: tabulate
Requires-Dist: numpy
Requires-Dist: munch
